{
    "sourceFile": "app/departments/new/page.tsx",
    "activeCommit": 0,
    "commits": [
        {
            "activePatchIndex": 14,
            "patches": [
                {
                    "date": 1764372534635,
                    "content": "Index: \n===================================================================\n--- \n+++ \n"
                },
                {
                    "date": 1764372602754,
                    "content": "Index: \n===================================================================\n--- \n+++ \n@@ -190,24 +190,8 @@\n                   onChange={handleInputChange}\r\n                   className=\"text-black mt-1 block w-full border border-slate-300 rounded-lg px-4 py-3 text-sm focus:outline-none focus:ring-2 focus:ring-slate-500 focus:border-slate-500 transition-all duration-200 bg-white shadow-sm\"\r\n                 />\r\n               </div>\r\n-\r\n-              <div>\r\n-                <label htmlFor=\"budget\" className=\"block text-sm font-semibold text-slate-700\">\r\n-                  Budget\r\n-                </label>\r\n-                <input\r\n-                  type=\"number\"\r\n-                  id=\"budget\"\r\n-                  name=\"budget\"\r\n-                  min=\"0\"\r\n-                  step=\"0.01\"\r\n-                  value={formData.budget || ''}\r\n-                  onChange={handleInputChange}\r\n-                  className=\"text-black mt-1 block w-full border border-slate-300 rounded-lg px-4 py-3 text-sm focus:outline-none focus:ring-2 focus:ring-slate-500 focus:border-slate-500 transition-all duration-200 bg-white shadow-sm\"\r\n-                />\r\n-              </div>\r\n             </div>\r\n \r\n             <div className=\"flex justify-end space-x-4 pt-6 border-t border-slate-200\">\r\n               <Button\r\n"
                },
                {
                    "date": 1764372619928,
                    "content": "Index: \n===================================================================\n--- \n+++ \n@@ -151,9 +151,9 @@\n                   id=\"headOfDepartmentId\"\r\n                   name=\"headOfDepartmentId\"\r\n                   value={formData.headOfDepartmentId || ''}\r\n                   onChange={handleInputChange}\r\n-                  className=\"text-black mt-1 block w-full border border-slate-300 rounded-lg px-4 py-3 text-sm focus:outline-none focus:ring-2 focus:ring-slate-500 focus:border-slate-500 transition-all duration-200 bg-white shadow-sm\"\r\n+                  className=\"text-black mt-2 block w-full border border-slate-300 rounded-lg px-4 py-3 text-sm focus:outline-none focus:ring-2 focus:ring-slate-500 focus:border-slate-500 transition-all duration-200 bg-white shadow-sm\"\r\n                 >\r\n                   <option value=\"\">Select Head of Department</option>\r\n                   {doctors.map(doctor => (\r\n                     <option key={doctor.id} value={doctor.id}>\r\n"
                },
                {
                    "date": 1764372625417,
                    "content": "Index: \n===================================================================\n--- \n+++ \n@@ -151,9 +151,9 @@\n                   id=\"headOfDepartmentId\"\r\n                   name=\"headOfDepartmentId\"\r\n                   value={formData.headOfDepartmentId || ''}\r\n                   onChange={handleInputChange}\r\n-                  className=\"text-black mt-2 block w-full border border-slate-300 rounded-lg px-4 py-3 text-sm focus:outline-none focus:ring-2 focus:ring-slate-500 focus:border-slate-500 transition-all duration-200 bg-white shadow-sm\"\r\n+                  className=\"text-black mt-1 block w-full border border-slate-300 rounded-lg px-4 py-3 text-sm focus:outline-none focus:ring-2 focus:ring-slate-500 focus:border-slate-500 transition-all duration-200 bg-white shadow-sm\"\r\n                 >\r\n                   <option value=\"\">Select Head of Department</option>\r\n                   {doctors.map(doctor => (\r\n                     <option key={doctor.id} value={doctor.id}>\r\n"
                },
                {
                    "date": 1764372693294,
                    "content": "Index: \n===================================================================\n--- \n+++ \n@@ -142,9 +142,10 @@\n                   className=\"text-black mt-1 block w-full border border-slate-300 rounded-lg px-4 py-3 text-sm focus:outline-none focus:ring-2 focus:ring-slate-500 focus:border-slate-500 transition-all duration-200 bg-white shadow-sm\"\r\n                 />\r\n               </div>\r\n \r\n-              <div>\r\n+              {/* Head of Department - full width row */}\r\n+              <div className=\"mb-4\">\r\n                 <label htmlFor=\"headOfDepartmentId\" className=\"block text-sm font-semibold text-slate-700\">\r\n                   Head of Department\r\n                 </label>\r\n                 <select\r\n@@ -162,36 +163,40 @@\n                   ))}\r\n                 </select>\r\n               </div>\r\n \r\n-              <div>\r\n-                <label htmlFor=\"establishedDate\" className=\"block text-sm font-semibold text-slate-700\">\r\n-                  Established Date *\r\n-                </label>\r\n-                <input\r\n-                  type=\"date\"\r\n-                  id=\"establishedDate\"\r\n-                  name=\"establishedDate\"\r\n-                  required\r\n-                  value={formData.establishedDate}\r\n-                  onChange={handleInputChange}\r\n-                  className=\"text-black mt-1 block w-full border border-slate-300 rounded-lg px-4 py-3 text-sm focus:outline-none focus:ring-2 focus:ring-slate-500 focus:border-slate-500 transition-all duration-200 bg-white shadow-sm\"\r\n-                />\r\n+              {/* Location and Established Date - same row */}\r\n+              <div className=\"flex gap-4 mb-4\">\r\n+                <div className=\"flex-1\">\r\n+                  <label htmlFor=\"location\" className=\"block text-sm font-semibold text-slate-700\">\r\n+                    Location\r\n+                  </label>\r\n+                  <input\r\n+                    type=\"text\"\r\n+                    id=\"location\"\r\n+                    name=\"location\"\r\n+                    value={formData.location}\r\n+                    onChange={handleInputChange}\r\n+                    className=\"text-black mt-1 block w-full border border-slate-300 rounded-lg px-4 py-3 text-sm focus:outline-none focus:ring-2 focus:ring-slate-500 focus:border-slate-500 transition-all duration-200 bg-white shadow-sm\"\r\n+                  />\r\n+                </div>\r\n+\r\n+                <div className=\"flex-1\">\r\n+                  <label htmlFor=\"establishedDate\" className=\"block text-sm font-semibold text-slate-700\">\r\n+                    Established Date *\r\n+                  </label>\r\n+                  <input\r\n+                    type=\"date\"\r\n+                    id=\"establishedDate\"\r\n+                    name=\"establishedDate\"\r\n+                    required\r\n+                    value={formData.establishedDate}\r\n+                    onChange={handleInputChange}\r\n+                    className=\"text-black mt-1 block w-full border border-slate-300 rounded-lg px-4 py-3 text-sm focus:outline-none focus:ring-2 focus:ring-slate-500 focus:border-slate-500 transition-all duration-200 bg-white shadow-sm\"\r\n+                  />\r\n+                </div>\r\n               </div>\r\n \r\n-              <div>\r\n-                <label htmlFor=\"location\" className=\"block text-sm font-semibold text-slate-700\">\r\n-                  Location\r\n-                </label>\r\n-                <input\r\n-                  type=\"text\"\r\n-                  id=\"location\"\r\n-                  name=\"location\"\r\n-                  value={formData.location}\r\n-                  onChange={handleInputChange}\r\n-                  className=\"text-black mt-1 block w-full border border-slate-300 rounded-lg px-4 py-3 text-sm focus:outline-none focus:ring-2 focus:ring-slate-500 focus:border-slate-500 transition-all duration-200 bg-white shadow-sm\"\r\n-                />\r\n-              </div>\r\n             </div>\r\n \r\n             <div className=\"flex justify-end space-x-4 pt-6 border-t border-slate-200\">\r\n               <Button\r\n"
                },
                {
                    "date": 1764372749256,
                    "content": "Index: \n===================================================================\n--- \n+++ \n@@ -142,30 +142,24 @@\n                   className=\"text-black mt-1 block w-full border border-slate-300 rounded-lg px-4 py-3 text-sm focus:outline-none focus:ring-2 focus:ring-slate-500 focus:border-slate-500 transition-all duration-200 bg-white shadow-sm\"\r\n                 />\r\n               </div>\r\n \r\n-              {/* Head of Department - full width row */}\r\n-              <div className=\"mb-4\">\r\n-                <label htmlFor=\"headOfDepartmentId\" className=\"block text-sm font-semibold text-slate-700\">\r\n-                  Head of Department\r\n-                </label>\r\n-                <select\r\n-                  id=\"headOfDepartmentId\"\r\n-                  name=\"headOfDepartmentId\"\r\n-                  value={formData.headOfDepartmentId || ''}\r\n-                  onChange={handleInputChange}\r\n-                  className=\"text-black mt-1 block w-full border border-slate-300 rounded-lg px-4 py-3 text-sm focus:outline-none focus:ring-2 focus:ring-slate-500 focus:border-slate-500 transition-all duration-200 bg-white shadow-sm\"\r\n-                >\r\n-                  <option value=\"\">Select Head of Department</option>\r\n-                  {doctors.map(doctor => (\r\n-                    <option key={doctor.id} value={doctor.id}>\r\n-                      Dr. {doctor.firstName} {doctor.lastName}\r\n-                    </option>\r\n-                  ))}\r\n-                </select>\r\n-              </div>\r\n+              {/* Head of Department - each doctor in a separate row */}\r\n+              {doctors.map((doctor) => (\r\n+                <div className=\"mb-4\" key={doctor.id}>\r\n+                  <label className=\"block text-sm font-semibold text-slate-700\">\r\n+                    Head of Department\r\n+                  </label>\r\n+                  <input\r\n+                    type=\"text\"\r\n+                    readOnly\r\n+                    value={`Dr. ${doctor.firstName} ${doctor.lastName}`}\r\n+                    className=\"text-black mt-1 block w-full border border-slate-300 rounded-lg px-4 py-3 text-sm bg-gray-100 shadow-sm\"\r\n+                  />\r\n+                </div>\r\n+              ))}\r\n \r\n-              {/* Location and Established Date - same row */}\r\n+              {/* Location and Established Date on the same row */}\r\n               <div className=\"flex gap-4 mb-4\">\r\n                 <div className=\"flex-1\">\r\n                   <label htmlFor=\"location\" className=\"block text-sm font-semibold text-slate-700\">\r\n                     Location\r\n"
                },
                {
                    "date": 1764372764437,
                    "content": "Index: \n===================================================================\n--- \n+++ \n@@ -142,55 +142,87 @@\n                   className=\"text-black mt-1 block w-full border border-slate-300 rounded-lg px-4 py-3 text-sm focus:outline-none focus:ring-2 focus:ring-slate-500 focus:border-slate-500 transition-all duration-200 bg-white shadow-sm\"\r\n                 />\r\n               </div>\r\n \r\n-              {/* Head of Department - each doctor in a separate row */}\r\n-              {doctors.map((doctor) => (\r\n-                <div className=\"mb-4\" key={doctor.id}>\r\n-                  <label className=\"block text-sm font-semibold text-slate-700\">\r\n-                    Head of Department\r\n-                  </label>\r\n-                  <input\r\n-                    type=\"text\"\r\n-                    readOnly\r\n-                    value={`Dr. ${doctor.firstName} ${doctor.lastName}`}\r\n-                    className=\"text-black mt-1 block w-full border border-slate-300 rounded-lg px-4 py-3 text-sm bg-gray-100 shadow-sm\"\r\n-                  />\r\n-                </div>\r\n-              ))}\r\n+              <div>\r\n+                <label htmlFor=\"headOfDepartmentId\" className=\"block text-sm font-semibold text-slate-700\">\r\n+                  Head of Department\r\n+                </label>\r\n+                <select\r\n+                  id=\"headOfDepartmentId\"\r\n+                  name=\"headOfDepartmentId\"\r\n+                  value={formData.headOfDepartmentId || ''}\r\n+                  onChange={handleInputChange}\r\n+                  className=\"text-black mt-1 block w-full border border-slate-300 rounded-lg px-4 py-3 text-sm focus:outline-none focus:ring-2 focus:ring-slate-500 focus:border-slate-500 transition-all duration-200 bg-white shadow-sm\"\r\n+                >\r\n+                  <option value=\"\">Select Head of Department</option>\r\n+                  {doctors.map(doctor => (\r\n+                    <option key={doctor.id} value={doctor.id}>\r\n+                      Dr. {doctor.firstName} {doctor.lastName}\r\n+                    </option>\r\n+                  ))}\r\n+                </select>\r\n+              </div>\r\n \r\n-              {/* Location and Established Date on the same row */}\r\n-              <div className=\"flex gap-4 mb-4\">\r\n-                <div className=\"flex-1\">\r\n-                  <label htmlFor=\"location\" className=\"block text-sm font-semibold text-slate-700\">\r\n-                    Location\r\n-                  </label>\r\n-                  <input\r\n-                    type=\"text\"\r\n-                    id=\"location\"\r\n-                    name=\"location\"\r\n-                    value={formData.location}\r\n-                    onChange={handleInputChange}\r\n-                    className=\"text-black mt-1 block w-full border border-slate-300 rounded-lg px-4 py-3 text-sm focus:outline-none focus:ring-2 focus:ring-slate-500 focus:border-slate-500 transition-all duration-200 bg-white shadow-sm\"\r\n-                  />\r\n-                </div>\r\n+              <div>\r\n+                <label htmlFor=\"establishedDate\" className=\"block text-sm font-semibold text-slate-700\">\r\n+                  Established Date *\r\n+                </label>\r\n+                <input\r\n+                  type=\"date\"\r\n+                  id=\"establishedDate\"\r\n+                  name=\"establishedDate\"\r\n+                  required\r\n+                  value={formData.establishedDate}\r\n+                  onChange={handleInputChange}\r\n+                  className=\"text-black mt-1 block w-full border border-slate-300 rounded-lg px-4 py-3 text-sm focus:outline-none focus:ring-2 focus:ring-slate-500 focus:border-slate-500 transition-all duration-200 bg-white shadow-sm\"\r\n+                />\r\n+              </div>\r\n \r\n-                <div className=\"flex-1\">\r\n-                  <label htmlFor=\"establishedDate\" className=\"block text-sm font-semibold text-slate-700\">\r\n-                    Established Date *\r\n-                  </label>\r\n-                  <input\r\n-                    type=\"date\"\r\n-                    id=\"establishedDate\"\r\n-                    name=\"establishedDate\"\r\n-                    required\r\n-                    value={formData.establishedDate}\r\n-                    onChange={handleInputChange}\r\n-                    className=\"text-black mt-1 block w-full border border-slate-300 rounded-lg px-4 py-3 text-sm focus:outline-none focus:ring-2 focus:ring-slate-500 focus:border-slate-500 transition-all duration-200 bg-white shadow-sm\"\r\n-                  />\r\n-                </div>\r\n+              <div>\r\n+                <label htmlFor=\"location\" className=\"block text-sm font-semibold text-slate-700\">\r\n+                  Location\r\n+                </label>\r\n+                <input\r\n+                  type=\"text\"\r\n+                  id=\"location\"\r\n+                  name=\"location\"\r\n+                  value={formData.location}\r\n+                  onChange={handleInputChange}\r\n+                  className=\"text-black mt-1 block w-full border border-slate-300 rounded-lg px-4 py-3 text-sm focus:outline-none focus:ring-2 focus:ring-slate-500 focus:border-slate-500 transition-all duration-200 bg-white shadow-sm\"\r\n+                />\r\n               </div>\r\n \r\n+              <div>\r\n+                <label htmlFor=\"website\" className=\"block text-sm font-semibold text-slate-700\">\r\n+                  Website\r\n+                </label>\r\n+                <input\r\n+                  type=\"url\"\r\n+                  id=\"website\"\r\n+                  name=\"website\"\r\n+                  value={formData.website}\r\n+                  onChange={handleInputChange}\r\n+                  placeholder=\"https://example.com\"\r\n+                  className=\"text-black mt-1 block w-full border border-slate-300 rounded-lg px-4 py-3 text-sm focus:outline-none focus:ring-2 focus:ring-slate-500 focus:border-slate-500 transition-all duration-200 bg-white shadow-sm\"\r\n+                />\r\n+              </div>\r\n+\r\n+              <div>\r\n+                <label htmlFor=\"budget\" className=\"block text-sm font-semibold text-slate-700\">\r\n+                  Budget\r\n+                </label>\r\n+                <input\r\n+                  type=\"number\"\r\n+                  id=\"budget\"\r\n+                  name=\"budget\"\r\n+                  min=\"0\"\r\n+                  step=\"0.01\"\r\n+                  value={formData.budget || ''}\r\n+                  onChange={handleInputChange}\r\n+                  className=\"text-black mt-1 block w-full border border-slate-300 rounded-lg px-4 py-3 text-sm focus:outline-none focus:ring-2 focus:ring-slate-500 focus:border-slate-500 transition-all duration-200 bg-white shadow-sm\"\r\n+                />\r\n+              </div>\r\n             </div>\r\n \r\n             <div className=\"flex justify-end space-x-4 pt-6 border-t border-slate-200\">\r\n               <Button\r\n"
                },
                {
                    "date": 1764372770446,
                    "content": "Index: \n===================================================================\n--- \n+++ \n@@ -190,39 +190,8 @@\n                   onChange={handleInputChange}\r\n                   className=\"text-black mt-1 block w-full border border-slate-300 rounded-lg px-4 py-3 text-sm focus:outline-none focus:ring-2 focus:ring-slate-500 focus:border-slate-500 transition-all duration-200 bg-white shadow-sm\"\r\n                 />\r\n               </div>\r\n-\r\n-              <div>\r\n-                <label htmlFor=\"website\" className=\"block text-sm font-semibold text-slate-700\">\r\n-                  Website\r\n-                </label>\r\n-                <input\r\n-                  type=\"url\"\r\n-                  id=\"website\"\r\n-                  name=\"website\"\r\n-                  value={formData.website}\r\n-                  onChange={handleInputChange}\r\n-                  placeholder=\"https://example.com\"\r\n-                  className=\"text-black mt-1 block w-full border border-slate-300 rounded-lg px-4 py-3 text-sm focus:outline-none focus:ring-2 focus:ring-slate-500 focus:border-slate-500 transition-all duration-200 bg-white shadow-sm\"\r\n-                />\r\n-              </div>\r\n-\r\n-              <div>\r\n-                <label htmlFor=\"budget\" className=\"block text-sm font-semibold text-slate-700\">\r\n-                  Budget\r\n-                </label>\r\n-                <input\r\n-                  type=\"number\"\r\n-                  id=\"budget\"\r\n-                  name=\"budget\"\r\n-                  min=\"0\"\r\n-                  step=\"0.01\"\r\n-                  value={formData.budget || ''}\r\n-                  onChange={handleInputChange}\r\n-                  className=\"text-black mt-1 block w-full border border-slate-300 rounded-lg px-4 py-3 text-sm focus:outline-none focus:ring-2 focus:ring-slate-500 focus:border-slate-500 transition-all duration-200 bg-white shadow-sm\"\r\n-                />\r\n-              </div>\r\n             </div>\r\n \r\n             <div className=\"flex justify-end space-x-4 pt-6 border-t border-slate-200\">\r\n               <Button\r\n"
                },
                {
                    "date": 1764372814230,
                    "content": "Index: \n===================================================================\n--- \n+++ \n@@ -143,28 +143,8 @@\n                 />\r\n               </div>\r\n \r\n               <div>\r\n-                <label htmlFor=\"headOfDepartmentId\" className=\"block text-sm font-semibold text-slate-700\">\r\n-                  Head of Department\r\n-                </label>\r\n-                <select\r\n-                  id=\"headOfDepartmentId\"\r\n-                  name=\"headOfDepartmentId\"\r\n-                  value={formData.headOfDepartmentId || ''}\r\n-                  onChange={handleInputChange}\r\n-                  className=\"text-black mt-1 block w-full border border-slate-300 rounded-lg px-4 py-3 text-sm focus:outline-none focus:ring-2 focus:ring-slate-500 focus:border-slate-500 transition-all duration-200 bg-white shadow-sm\"\r\n-                >\r\n-                  <option value=\"\">Select Head of Department</option>\r\n-                  {doctors.map(doctor => (\r\n-                    <option key={doctor.id} value={doctor.id}>\r\n-                      Dr. {doctor.firstName} {doctor.lastName}\r\n-                    </option>\r\n-                  ))}\r\n-                </select>\r\n-              </div>\r\n-\r\n-              <div>\r\n                 <label htmlFor=\"establishedDate\" className=\"block text-sm font-semibold text-slate-700\">\r\n                   Established Date *\r\n                 </label>\r\n                 <input\r\n@@ -192,8 +172,28 @@\n                 />\r\n               </div>\r\n             </div>\r\n \r\n+            <div>\r\n+              <label htmlFor=\"headOfDepartmentId\" className=\"block text-sm font-semibold text-slate-700\">\r\n+                Head of Department\r\n+              </label>\r\n+              <select\r\n+                id=\"headOfDepartmentId\"\r\n+                name=\"headOfDepartmentId\"\r\n+                value={formData.headOfDepartmentId || ''}\r\n+                onChange={handleInputChange}\r\n+                className=\"text-black mt-1 block w-full border border-slate-300 rounded-lg px-4 py-3 text-sm focus:outline-none focus:ring-2 focus:ring-slate-500 focus:border-slate-500 transition-all duration-200 bg-white shadow-sm\"\r\n+              >\r\n+                <option value=\"\">Select Head of Department</option>\r\n+                {doctors.map(doctor => (\r\n+                  <option key={doctor.id} value={doctor.id}>\r\n+                    Dr. {doctor.firstName} {doctor.lastName}\r\n+                  </option>\r\n+                ))}\r\n+              </select>\r\n+            </div>\r\n+\r\n             <div className=\"flex justify-end space-x-4 pt-6 border-t border-slate-200\">\r\n               <Button\r\n                 type=\"button\"\r\n                 variant=\"outline\"\r\n"
                },
                {
                    "date": 1764373924624,
                    "content": "Index: \n===================================================================\n--- \n+++ \n@@ -41,8 +41,9 @@\n     }\r\n   };\r\n \r\n   const handleInputChange = (e: React.ChangeEvent<HTMLInputElement | HTMLSelectElement | HTMLTextAreaElement>) => {\r\n+    z\r\n   };\r\n \r\n   const handleSubmit = async (e: React.FormEvent) => {\r\n     e.preventDefault();\r\n@@ -54,13 +55,13 @@\n \r\n       if (response.success) {\r\n         router.push('/departments');\r\n       } else {\r\n-        setError('Failed to create the new Department');\r\n+        setError('Failed to create department');\r\n       }\r\n     } catch (err) {\r\n-      setError('An error occurred while creating the Department');\r\n-      console.error('Error creating Department:', err);\r\n+      setError('An error occurred while creating the department');\r\n+      console.error('Error creating department:', err);\r\n     } finally {\r\n       setLoading(false);\r\n     }\r\n   };\r\n@@ -69,9 +70,9 @@\n     <div className=\"max-w-2xl mx-auto\">\r\n       <div className=\"mb-6\">\r\n         <h1 className=\"text-3xl font-bold text-slate-900\">Add New Department</h1>\r\n         <p className=\"mt-2 text-base text-slate-600\">\r\n-          Enter new Department information below\r\n+          Enter the department information below\r\n         </p>\r\n       </div>\r\n \r\n       {error && (\r\n@@ -143,8 +144,28 @@\n                 />\r\n               </div>\r\n \r\n               <div>\r\n+                <label htmlFor=\"headOfDepartmentId\" className=\"block text-sm font-semibold text-slate-700\">\r\n+                  Head of Department\r\n+                </label>\r\n+                <select\r\n+                  id=\"headOfDepartmentId\"\r\n+                  name=\"headOfDepartmentId\"\r\n+                  value={formData.headOfDepartmentId || ''}\r\n+                  onChange={handleInputChange}\r\n+                  className=\"text-black mt-1 block w-full border border-slate-300 rounded-lg px-4 py-3 text-sm focus:outline-none focus:ring-2 focus:ring-slate-500 focus:border-slate-500 transition-all duration-200 bg-white shadow-sm\"\r\n+                >\r\n+                  <option value=\"\">Select Head of Department</option>\r\n+                  {doctors.map(doctor => (\r\n+                    <option key={doctor.id} value={doctor.id}>\r\n+                      Dr. {doctor.firstName} {doctor.lastName}\r\n+                    </option>\r\n+                  ))}\r\n+                </select>\r\n+              </div>\r\n+\r\n+              <div>\r\n                 <label htmlFor=\"establishedDate\" className=\"block text-sm font-semibold text-slate-700\">\r\n                   Established Date *\r\n                 </label>\r\n                 <input\r\n@@ -170,28 +191,67 @@\n                   onChange={handleInputChange}\r\n                   className=\"text-black mt-1 block w-full border border-slate-300 rounded-lg px-4 py-3 text-sm focus:outline-none focus:ring-2 focus:ring-slate-500 focus:border-slate-500 transition-all duration-200 bg-white shadow-sm\"\r\n                 />\r\n               </div>\r\n-            </div>\r\n \r\n-            <div>\r\n-              <label htmlFor=\"headOfDepartmentId\" className=\"block text-sm font-semibold text-slate-700\">\r\n-                Head of Department\r\n-              </label>\r\n-              <select\r\n-                id=\"headOfDepartmentId\"\r\n-                name=\"headOfDepartmentId\"\r\n-                value={formData.headOfDepartmentId || ''}\r\n-                onChange={handleInputChange}\r\n-                className=\"text-black mt-1 block w-full border border-slate-300 rounded-lg px-4 py-3 text-sm focus:outline-none focus:ring-2 focus:ring-slate-500 focus:border-slate-500 transition-all duration-200 bg-white shadow-sm\"\r\n-              >\r\n-                <option value=\"\">Select Head of Department</option>\r\n-                {doctors.map(doctor => (\r\n-                  <option key={doctor.id} value={doctor.id}>\r\n-                    Dr. {doctor.firstName} {doctor.lastName}\r\n-                  </option>\r\n-                ))}\r\n-              </select>\r\n+              <div>\r\n+                <label htmlFor=\"phoneNumber\" className=\"block text-sm font-semibold text-slate-700\">\r\n+                  Phone Number\r\n+                </label>\r\n+                <input\r\n+                  type=\"tel\"\r\n+                  id=\"phoneNumber\"\r\n+                  name=\"phoneNumber\"\r\n+                  value={formData.phoneNumber}\r\n+                  onChange={handleInputChange}\r\n+                  className=\"text-black mt-1 block w-full border border-slate-300 rounded-lg px-4 py-3 text-sm focus:outline-none focus:ring-2 focus:ring-slate-500 focus:border-slate-500 transition-all duration-200 bg-white shadow-sm\"\r\n+                />\r\n+              </div>\r\n+\r\n+              <div>\r\n+                <label htmlFor=\"email\" className=\"block text-sm font-semibold text-slate-700\">\r\n+                  Email\r\n+                </label>\r\n+                <input\r\n+                  type=\"email\"\r\n+                  id=\"email\"\r\n+                  name=\"email\"\r\n+                  value={formData.email}\r\n+                  onChange={handleInputChange}\r\n+                  className=\"text-black mt-1 block w-full border border-slate-300 rounded-lg px-4 py-3 text-sm focus:outline-none focus:ring-2 focus:ring-slate-500 focus:border-slate-500 transition-all duration-200 bg-white shadow-sm\"\r\n+                />\r\n+              </div>\r\n+\r\n+              <div>\r\n+                <label htmlFor=\"website\" className=\"block text-sm font-semibold text-slate-700\">\r\n+                  Website\r\n+                </label>\r\n+                <input\r\n+                  type=\"url\"\r\n+                  id=\"website\"\r\n+                  name=\"website\"\r\n+                  value={formData.website}\r\n+                  onChange={handleInputChange}\r\n+                  placeholder=\"https://example.com\"\r\n+                  className=\"text-black mt-1 block w-full border border-slate-300 rounded-lg px-4 py-3 text-sm focus:outline-none focus:ring-2 focus:ring-slate-500 focus:border-slate-500 transition-all duration-200 bg-white shadow-sm\"\r\n+                />\r\n+              </div>\r\n+\r\n+              <div>\r\n+                <label htmlFor=\"budget\" className=\"block text-sm font-semibold text-slate-700\">\r\n+                  Budget\r\n+                </label>\r\n+                <input\r\n+                  type=\"number\"\r\n+                  id=\"budget\"\r\n+                  name=\"budget\"\r\n+                  min=\"0\"\r\n+                  step=\"0.01\"\r\n+                  value={formData.budget || ''}\r\n+                  onChange={handleInputChange}\r\n+                  className=\"text-black mt-1 block w-full border border-slate-300 rounded-lg px-4 py-3 text-sm focus:outline-none focus:ring-2 focus:ring-slate-500 focus:border-slate-500 transition-all duration-200 bg-white shadow-sm\"\r\n+                />\r\n+              </div>\r\n             </div>\r\n \r\n             <div className=\"flex justify-end space-x-4 pt-6 border-t border-slate-200\">\r\n               <Button\r\n"
                },
                {
                    "date": 1764373937393,
                    "content": "Index: \n===================================================================\n--- \n+++ \n@@ -41,9 +41,13 @@\n     }\r\n   };\r\n \r\n   const handleInputChange = (e: React.ChangeEvent<HTMLInputElement | HTMLSelectElement | HTMLTextAreaElement>) => {\r\n-    z\r\n+    const { name, value } = e.target;\r\n+    setFormData(prev => ({\r\n+      ...prev,\r\n+      [name]: name === 'budget' ? (value ? parseFloat(value) : undefined) : value,\r\n+    }));\r\n   };\r\n \r\n   const handleSubmit = async (e: React.FormEvent) => {\r\n     e.preventDefault();\r\n"
                },
                {
                    "date": 1764373944342,
                    "content": "Index: \n===================================================================\n--- \n+++ \n@@ -41,13 +41,9 @@\n     }\r\n   };\r\n \r\n   const handleInputChange = (e: React.ChangeEvent<HTMLInputElement | HTMLSelectElement | HTMLTextAreaElement>) => {\r\n-    const { name, value } = e.target;\r\n-    setFormData(prev => ({\r\n-      ...prev,\r\n-      [name]: name === 'budget' ? (value ? parseFloat(value) : undefined) : value,\r\n-    }));\r\n+\r\n   };\r\n \r\n   const handleSubmit = async (e: React.FormEvent) => {\r\n     e.preventDefault();\r\n"
                },
                {
                    "date": 1764373951524,
                    "content": "Index: \n===================================================================\n--- \n+++ \n@@ -41,9 +41,8 @@\n     }\r\n   };\r\n \r\n   const handleInputChange = (e: React.ChangeEvent<HTMLInputElement | HTMLSelectElement | HTMLTextAreaElement>) => {\r\n-\r\n   };\r\n \r\n   const handleSubmit = async (e: React.FormEvent) => {\r\n     e.preventDefault();\r\n@@ -55,13 +54,13 @@\n \r\n       if (response.success) {\r\n         router.push('/departments');\r\n       } else {\r\n-        setError('Failed to create department');\r\n+        setError('Failed to create the new Department');\r\n       }\r\n     } catch (err) {\r\n-      setError('An error occurred while creating the department');\r\n-      console.error('Error creating department:', err);\r\n+      setError('An error occurred while creating the Department');\r\n+      console.error('Error creating Department:', err);\r\n     } finally {\r\n       setLoading(false);\r\n     }\r\n   };\r\n@@ -70,9 +69,9 @@\n     <div className=\"max-w-2xl mx-auto\">\r\n       <div className=\"mb-6\">\r\n         <h1 className=\"text-3xl font-bold text-slate-900\">Add New Department</h1>\r\n         <p className=\"mt-2 text-base text-slate-600\">\r\n-          Enter the department information below\r\n+          Enter new Department information below\r\n         </p>\r\n       </div>\r\n \r\n       {error && (\r\n@@ -144,28 +143,8 @@\n                 />\r\n               </div>\r\n \r\n               <div>\r\n-                <label htmlFor=\"headOfDepartmentId\" className=\"block text-sm font-semibold text-slate-700\">\r\n-                  Head of Department\r\n-                </label>\r\n-                <select\r\n-                  id=\"headOfDepartmentId\"\r\n-                  name=\"headOfDepartmentId\"\r\n-                  value={formData.headOfDepartmentId || ''}\r\n-                  onChange={handleInputChange}\r\n-                  className=\"text-black mt-1 block w-full border border-slate-300 rounded-lg px-4 py-3 text-sm focus:outline-none focus:ring-2 focus:ring-slate-500 focus:border-slate-500 transition-all duration-200 bg-white shadow-sm\"\r\n-                >\r\n-                  <option value=\"\">Select Head of Department</option>\r\n-                  {doctors.map(doctor => (\r\n-                    <option key={doctor.id} value={doctor.id}>\r\n-                      Dr. {doctor.firstName} {doctor.lastName}\r\n-                    </option>\r\n-                  ))}\r\n-                </select>\r\n-              </div>\r\n-\r\n-              <div>\r\n                 <label htmlFor=\"establishedDate\" className=\"block text-sm font-semibold text-slate-700\">\r\n                   Established Date *\r\n                 </label>\r\n                 <input\r\n@@ -191,67 +170,28 @@\n                   onChange={handleInputChange}\r\n                   className=\"text-black mt-1 block w-full border border-slate-300 rounded-lg px-4 py-3 text-sm focus:outline-none focus:ring-2 focus:ring-slate-500 focus:border-slate-500 transition-all duration-200 bg-white shadow-sm\"\r\n                 />\r\n               </div>\r\n+            </div>\r\n \r\n-              <div>\r\n-                <label htmlFor=\"phoneNumber\" className=\"block text-sm font-semibold text-slate-700\">\r\n-                  Phone Number\r\n-                </label>\r\n-                <input\r\n-                  type=\"tel\"\r\n-                  id=\"phoneNumber\"\r\n-                  name=\"phoneNumber\"\r\n-                  value={formData.phoneNumber}\r\n-                  onChange={handleInputChange}\r\n-                  className=\"text-black mt-1 block w-full border border-slate-300 rounded-lg px-4 py-3 text-sm focus:outline-none focus:ring-2 focus:ring-slate-500 focus:border-slate-500 transition-all duration-200 bg-white shadow-sm\"\r\n-                />\r\n-              </div>\r\n-\r\n-              <div>\r\n-                <label htmlFor=\"email\" className=\"block text-sm font-semibold text-slate-700\">\r\n-                  Email\r\n-                </label>\r\n-                <input\r\n-                  type=\"email\"\r\n-                  id=\"email\"\r\n-                  name=\"email\"\r\n-                  value={formData.email}\r\n-                  onChange={handleInputChange}\r\n-                  className=\"text-black mt-1 block w-full border border-slate-300 rounded-lg px-4 py-3 text-sm focus:outline-none focus:ring-2 focus:ring-slate-500 focus:border-slate-500 transition-all duration-200 bg-white shadow-sm\"\r\n-                />\r\n-              </div>\r\n-\r\n-              <div>\r\n-                <label htmlFor=\"website\" className=\"block text-sm font-semibold text-slate-700\">\r\n-                  Website\r\n-                </label>\r\n-                <input\r\n-                  type=\"url\"\r\n-                  id=\"website\"\r\n-                  name=\"website\"\r\n-                  value={formData.website}\r\n-                  onChange={handleInputChange}\r\n-                  placeholder=\"https://example.com\"\r\n-                  className=\"text-black mt-1 block w-full border border-slate-300 rounded-lg px-4 py-3 text-sm focus:outline-none focus:ring-2 focus:ring-slate-500 focus:border-slate-500 transition-all duration-200 bg-white shadow-sm\"\r\n-                />\r\n-              </div>\r\n-\r\n-              <div>\r\n-                <label htmlFor=\"budget\" className=\"block text-sm font-semibold text-slate-700\">\r\n-                  Budget\r\n-                </label>\r\n-                <input\r\n-                  type=\"number\"\r\n-                  id=\"budget\"\r\n-                  name=\"budget\"\r\n-                  min=\"0\"\r\n-                  step=\"0.01\"\r\n-                  value={formData.budget || ''}\r\n-                  onChange={handleInputChange}\r\n-                  className=\"text-black mt-1 block w-full border border-slate-300 rounded-lg px-4 py-3 text-sm focus:outline-none focus:ring-2 focus:ring-slate-500 focus:border-slate-500 transition-all duration-200 bg-white shadow-sm\"\r\n-                />\r\n-              </div>\r\n+            <div>\r\n+              <label htmlFor=\"headOfDepartmentId\" className=\"block text-sm font-semibold text-slate-700\">\r\n+                Head of Department\r\n+              </label>\r\n+              <select\r\n+                id=\"headOfDepartmentId\"\r\n+                name=\"headOfDepartmentId\"\r\n+                value={formData.headOfDepartmentId || ''}\r\n+                onChange={handleInputChange}\r\n+                className=\"text-black mt-1 block w-full border border-slate-300 rounded-lg px-4 py-3 text-sm focus:outline-none focus:ring-2 focus:ring-slate-500 focus:border-slate-500 transition-all duration-200 bg-white shadow-sm\"\r\n+              >\r\n+                <option value=\"\">Select Head of Department</option>\r\n+                {doctors.map(doctor => (\r\n+                  <option key={doctor.id} value={doctor.id}>\r\n+                    Dr. {doctor.firstName} {doctor.lastName}\r\n+                  </option>\r\n+                ))}\r\n+              </select>\r\n             </div>\r\n \r\n             <div className=\"flex justify-end space-x-4 pt-6 border-t border-slate-200\">\r\n               <Button\r\n@@ -273,5 +213,4 @@\n       </Card>\r\n     </div>\r\n   );\r\n }\r\n-\r\n"
                },
                {
                    "date": 1764373958659,
                    "content": "Index: \n===================================================================\n--- \n+++ \n@@ -22,9 +22,8 @@\n     location: '',\r\n     phoneNumber: '',\r\n     email: '',\r\n     website: '',\r\n-    budget: undefined,\r\n   });\r\n \r\n   useEffect(() => {\r\n     loadDoctors();\r\n"
                },
                {
                    "date": 1764373979239,
                    "content": "Index: \n===================================================================\n--- \n+++ \n@@ -21,9 +21,9 @@\n     establishedDate: new Date().toISOString().split('T')[0],\r\n     location: '',\r\n     phoneNumber: '',\r\n     email: '',\r\n-    website: '',\r\n+    website: ''\r\n   });\r\n \r\n   useEffect(() => {\r\n     loadDoctors();\r\n"
                }
            ],
            "date": 1764372534635,
            "name": "Commit-0",
            "content": "'use client';\r\n\r\nimport { useState, useEffect } from 'react';\r\nimport { useRouter } from 'next/navigation';\r\nimport { CreateDepartmentRequest } from '../../../types';\r\nimport { apiService } from '../../../services/api';\r\nimport { Card, CardContent, CardHeader } from '../../../components/ui/Card';\r\nimport Button from '../../../components/ui/Button';\r\n\r\nexport default function NewDepartmentPage() {\r\n  const router = useRouter();\r\n  const [loading, setLoading] = useState(false);\r\n  const [error, setError] = useState<string | null>(null);\r\n  const [doctors, setDoctors] = useState<{ id: string; firstName: string; lastName: string }[]>([]);\r\n\r\n  const [formData, setFormData] = useState<CreateDepartmentRequest>({\r\n    name: '',\r\n    code: '',\r\n    description: '',\r\n    headOfDepartmentId: '',\r\n    establishedDate: new Date().toISOString().split('T')[0],\r\n    location: '',\r\n    phoneNumber: '',\r\n    email: '',\r\n    website: '',\r\n    budget: undefined,\r\n  });\r\n\r\n  useEffect(() => {\r\n    loadDoctors();\r\n  }, []);\r\n\r\n  const loadDoctors = async () => {\r\n    try {\r\n      const response = await apiService.getDoctors();\r\n      if (response.success) {\r\n        setDoctors(response.data.map(d => ({ id: d.id, firstName: d.firstName, lastName: d.lastName })));\r\n      }\r\n    } catch (err) {\r\n      console.error('Error loading doctors:', err);\r\n    }\r\n  };\r\n\r\n  const handleInputChange = (e: React.ChangeEvent<HTMLInputElement | HTMLSelectElement | HTMLTextAreaElement>) => {\r\n  };\r\n\r\n  const handleSubmit = async (e: React.FormEvent) => {\r\n    e.preventDefault();\r\n    setLoading(true);\r\n    setError(null);\r\n\r\n    try {\r\n      const response = await apiService.createDepartment(formData);\r\n\r\n      if (response.success) {\r\n        router.push('/departments');\r\n      } else {\r\n        setError('Failed to create the new Department');\r\n      }\r\n    } catch (err) {\r\n      setError('An error occurred while creating the Department');\r\n      console.error('Error creating Department:', err);\r\n    } finally {\r\n      setLoading(false);\r\n    }\r\n  };\r\n\r\n  return (\r\n    <div className=\"max-w-2xl mx-auto\">\r\n      <div className=\"mb-6\">\r\n        <h1 className=\"text-3xl font-bold text-slate-900\">Add New Department</h1>\r\n        <p className=\"mt-2 text-base text-slate-600\">\r\n          Enter new Department information below\r\n        </p>\r\n      </div>\r\n\r\n      {error && (\r\n        <div className=\"mb-6 bg-red-50 border border-red-200 rounded-md p-4\">\r\n          <div className=\"flex\">\r\n            <div className=\"flex-shrink-0\">\r\n              <svg className=\"h-5 w-5 text-red-400\" viewBox=\"0 0 20 20\" fill=\"currentColor\">\r\n                <path fillRule=\"evenodd\" d=\"M10 18a8 8 0 100-16 8 8 0 000 16zM8.707 7.293a1 1 0 00-1.414 1.414L8.586 10l-1.293 1.293a1 1 0 101.414 1.414L10 11.414l1.293 1.293a1 1 0 001.414-1.414L11.414 10l1.293-1.293a1 1 0 00-1.414-1.414L10 8.586 8.707 7.293z\" clipRule=\"evenodd\" />\r\n              </svg>\r\n            </div>\r\n            <div className=\"ml-3\">\r\n              <h3 className=\"text-sm font-medium text-red-800\">Error</h3>\r\n              <div className=\"mt-2 text-sm text-red-700\">\r\n                <p>{error}</p>\r\n              </div>\r\n            </div>\r\n          </div>\r\n        </div>\r\n      )}\r\n\r\n      <Card>\r\n        <CardHeader>\r\n          <h2 className=\"text-lg font-semibold text-slate-900\">Department Information</h2>\r\n        </CardHeader>\r\n        <CardContent>\r\n          <form onSubmit={handleSubmit} className=\"space-y-6\">\r\n            <div className=\"grid grid-cols-1 md:grid-cols-2 gap-6\">\r\n              <div>\r\n                <label htmlFor=\"name\" className=\"block text-sm font-semibold text-slate-700\">\r\n                  Department Name *\r\n                </label>\r\n                <input\r\n                  type=\"text\"\r\n                  id=\"name\"\r\n                  name=\"name\"\r\n                  required\r\n                  value={formData.name}\r\n                  onChange={handleInputChange}\r\n                  className=\"text-black mt-1 block w-full border border-slate-300 rounded-lg px-4 py-3 text-sm focus:outline-none focus:ring-2 focus:ring-slate-500 focus:border-slate-500 transition-all duration-200 bg-white shadow-sm\"\r\n                />\r\n              </div>\r\n\r\n              <div>\r\n                <label htmlFor=\"code\" className=\"block text-sm font-semibold text-slate-700\">\r\n                  Department Code *\r\n                </label>\r\n                <input\r\n                  type=\"text\"\r\n                  id=\"code\"\r\n                  name=\"code\"\r\n                  required\r\n                  value={formData.code}\r\n                  onChange={handleInputChange}\r\n                  className=\"text-black mt-1 block w-full border border-slate-300 rounded-lg px-4 py-3 text-sm focus:outline-none focus:ring-2 focus:ring-slate-500 focus:border-slate-500 transition-all duration-200 bg-white shadow-sm\"\r\n                />\r\n              </div>\r\n\r\n              <div className=\"md:col-span-2\">\r\n                <label htmlFor=\"description\" className=\"block text-sm font-semibold text-slate-700\">\r\n                  Description\r\n                </label>\r\n                <textarea\r\n                  id=\"description\"\r\n                  name=\"description\"\r\n                  rows={3}\r\n                  value={formData.description}\r\n                  onChange={handleInputChange}\r\n                  className=\"text-black mt-1 block w-full border border-slate-300 rounded-lg px-4 py-3 text-sm focus:outline-none focus:ring-2 focus:ring-slate-500 focus:border-slate-500 transition-all duration-200 bg-white shadow-sm\"\r\n                />\r\n              </div>\r\n\r\n              <div>\r\n                <label htmlFor=\"headOfDepartmentId\" className=\"block text-sm font-semibold text-slate-700\">\r\n                  Head of Department\r\n                </label>\r\n                <select\r\n                  id=\"headOfDepartmentId\"\r\n                  name=\"headOfDepartmentId\"\r\n                  value={formData.headOfDepartmentId || ''}\r\n                  onChange={handleInputChange}\r\n                  className=\"text-black mt-1 block w-full border border-slate-300 rounded-lg px-4 py-3 text-sm focus:outline-none focus:ring-2 focus:ring-slate-500 focus:border-slate-500 transition-all duration-200 bg-white shadow-sm\"\r\n                >\r\n                  <option value=\"\">Select Head of Department</option>\r\n                  {doctors.map(doctor => (\r\n                    <option key={doctor.id} value={doctor.id}>\r\n                      Dr. {doctor.firstName} {doctor.lastName}\r\n                    </option>\r\n                  ))}\r\n                </select>\r\n              </div>\r\n\r\n              <div>\r\n                <label htmlFor=\"establishedDate\" className=\"block text-sm font-semibold text-slate-700\">\r\n                  Established Date *\r\n                </label>\r\n                <input\r\n                  type=\"date\"\r\n                  id=\"establishedDate\"\r\n                  name=\"establishedDate\"\r\n                  required\r\n                  value={formData.establishedDate}\r\n                  onChange={handleInputChange}\r\n                  className=\"text-black mt-1 block w-full border border-slate-300 rounded-lg px-4 py-3 text-sm focus:outline-none focus:ring-2 focus:ring-slate-500 focus:border-slate-500 transition-all duration-200 bg-white shadow-sm\"\r\n                />\r\n              </div>\r\n\r\n              <div>\r\n                <label htmlFor=\"location\" className=\"block text-sm font-semibold text-slate-700\">\r\n                  Location\r\n                </label>\r\n                <input\r\n                  type=\"text\"\r\n                  id=\"location\"\r\n                  name=\"location\"\r\n                  value={formData.location}\r\n                  onChange={handleInputChange}\r\n                  className=\"text-black mt-1 block w-full border border-slate-300 rounded-lg px-4 py-3 text-sm focus:outline-none focus:ring-2 focus:ring-slate-500 focus:border-slate-500 transition-all duration-200 bg-white shadow-sm\"\r\n                />\r\n              </div>\r\n\r\n              <div>\r\n                <label htmlFor=\"budget\" className=\"block text-sm font-semibold text-slate-700\">\r\n                  Budget\r\n                </label>\r\n                <input\r\n                  type=\"number\"\r\n                  id=\"budget\"\r\n                  name=\"budget\"\r\n                  min=\"0\"\r\n                  step=\"0.01\"\r\n                  value={formData.budget || ''}\r\n                  onChange={handleInputChange}\r\n                  className=\"text-black mt-1 block w-full border border-slate-300 rounded-lg px-4 py-3 text-sm focus:outline-none focus:ring-2 focus:ring-slate-500 focus:border-slate-500 transition-all duration-200 bg-white shadow-sm\"\r\n                />\r\n              </div>\r\n            </div>\r\n\r\n            <div className=\"flex justify-end space-x-4 pt-6 border-t border-slate-200\">\r\n              <Button\r\n                type=\"button\"\r\n                variant=\"outline\"\r\n                onClick={() => router.back()}\r\n              >\r\n                Cancel\r\n              </Button>\r\n              <Button\r\n                type=\"submit\"\r\n                loading={loading}\r\n              >\r\n                Create Department\r\n              </Button>\r\n            </div>\r\n          </form>\r\n        </CardContent>\r\n      </Card>\r\n    </div>\r\n  );\r\n}\r\n\r\n"
        }
    ]
}